py3_wget/__init__.py
py3_wget/__version__.py
py3_wget/cksum.py
py3_wget/main.py
py3_wget/py.typed
py3_wget-1.0.13.dist-info/licenses/LICENSE
tests/__init__.py
tests/test_main.py
py3_wget-1.0.13.dist-info/METADATA
py3_wget-1.0.13.dist-info/WHEEL
py3_wget-1.0.13.dist-info/top_level.txt
py3_wget-1.0.13.dist-info/RECORD
